{
	"head": {
		"meta": [
			{
				"name": "keywords",
				"content": "中原铁道,窄轨,河南窄轨,铁道博物馆"
			},
			{
				"name": "description",
				"content": "上世纪五十年代末期，河南省开始兴办地方铁路。半个多世纪间，先后有16条地方铁路线路横贯中原大地，长度逾1,600千米。欢迎来到中原铁道 (数字) 博物馆，开启一场轨距762毫米的旅程。"
			}
		]
	},
	"update":{
		"info":"<b>2022年2月下</b> · 数字博物馆一期更新内容 ›",
		"link":"/about/update"
	},
  "specials":{
    "info":"<h6>中原铁道(数字)博物馆 × 豫见铁路公园</h6><h3>五一小长假，<br>小火车再出发！</h3><br><small>专题报道即将呈现 ›</small>",
    "link":"/404",
    "bgImg":"https://s1.ax1x.com/2022/04/30/Lz6ujJ.png",
    "colorBg":"#314c1e",
    "color":"#ccedb5"
  },
	"jumboItems":[
		{
			"title": "仍在运用的老河口机车转盘",
			"subTitle": "湖北老河口 · 光化水泥厂",
			"jumboImg": "https://s4.ax1x.com/2022/01/19/7DIvjA.jpg",
			"isActive": true,
			"link":"./#"
		},
		{
			"title": "废弃机车中的前方展望",
			"subTitle": "河南登封 · 朝杞铁路炮房沟站",
			"jumboImg": "https://s4.ax1x.com/2022/01/19/7DIjcd.jpg",
			"link":"/virtualtour/chaoqi"
		},
		{
			"title": "2007年地铁改制后的印章",
			"subTitle": "河南新密 · 平陌车站站房",
			"jumboImg": "https://s4.ax1x.com/2022/01/19/7DIznI.jpg",
			"link":"/virtualtour/chaoqi"
		},
		{
			"title": "夕阳下的扶沟车站",
			"subTitle": "河南周口 · 许郸铁路扶沟车站",
			"jumboImg": "https://s4.ax1x.com/2022/01/19/7DIX1H.jpg",
			"link":"/virtualtour/xudan"
		},
		{
			"title": "贾鲁河畔跃进纪念碑",
			"subTitle": "河南周口 · 许郸铁路扶沟贾鲁河桥",
			"jumboImg": "https://s4.ax1x.com/2022/01/19/7DIO9e.jpg",
			"link":"/virtualtour/xudan"
		}
	],
	"categories":[
		{
			"title": "漫游",
			"subtitle": "Virtual Tour",
			"details": "坐地日行千万里，探寻中原大地硕果累累的轨道遗迹",
			"bgImg": "https://s4.ax1x.com/2022/01/19/7DLmDJ.jpg",
			"link": "/virtualtour"
		},
		{
			"title": "车辆",
			"subtitle": "Depot",
			"details": "动静交错之间，一探它们曾经风驰电掣的身影",
			"bgImg": "https://s4.ax1x.com/2022/01/19/7DLnb9.jpg",
			"link": "/depot"
		},
		{
			"title": "建筑",
			"subtitle": "Architecture",
			"details": "车站、桥梁、隧道，领略地方铁路建筑风采",
			"bgImg": "https://s4.ax1x.com/2022/01/19/7DLKER.jpg",
			"link": "/architecture"
		},
		{
			"title": "生活",
			"subtitle": "Life",
			"details": "交通连接人间世，实物展再现地方铁路运营景象",
			"bgImg": "https://s4.ax1x.com/2022/01/19/7DLMU1.jpg",
			"link": "/life"
		},
		{
			"title": "历史",
			"subtitle": "History",
			"details": "寸尺亦能去西东，讲述河南地方铁路的兴起发展",
			"bgImg": "https://s4.ax1x.com/2022/01/19/7DLeu4.jpg",
			"link": "/history"
		},			
		{
			"title": "研究",
			"subtitle": "Research",			
			"details": "提供研究河南地方铁路的资料和成果",
			"bgImg": "https://s4.ax1x.com/2022/01/19/7DLQ4x.jpg",
			"link": "/research"
		}
	]
}
